LICENCE
MANIFEST.in
README.md
setup.py
paginate_whoosh/__init__.py
paginate_whoosh.egg-info/PKG-INFO
paginate_whoosh.egg-info/SOURCES.txt
paginate_whoosh.egg-info/dependency_links.txt
paginate_whoosh.egg-info/not-zip-safe
paginate_whoosh.egg-info/requires.txt
paginate_whoosh.egg-info/top_level.txt