Metadata-Version: 1.1
Name: paginate-whoosh
Version: 0.3
Summary: Extension to the paginate module to support Whoosh
Home-page: https://github.com/myriogon/paginate_whoosh
Author: Lukas Weissenböck
Author-email: lukas@lukes.space
License: MIT
Keywords: pagination paginate whoosh
Platform: UNKNOWN
Classifier: Programming Language :: Python :: 2
Classifier: Programming Language :: Python :: 3
Classifier: Intended Audience :: Developers
Classifier: Topic :: Software Development :: Libraries :: Python Modules
